CHANGELOG.txt
LICENCE.txt
MANIFEST.in
README.txt
setup.py
diet_linear_algebra/__init__.py
dietlinearalgebra.egg-info/PKG-INFO
dietlinearalgebra.egg-info/SOURCES.txt
dietlinearalgebra.egg-info/dependency_links.txt
dietlinearalgebra.egg-info/top_level.txt
linalg/__init__.py
linalg/test.py